{
  "slug": "confidence-paradox-imposter-syndrome",
  "title": "The Confidence Paradox: Why You're Most Insecure Exactly Where You're Most Competent",
  "category": "Mindset",
  "image": "photo-1573496359142-b8d87734a5a2",
  "excerpt": "The more skilled you become, the more you doubt yourself. Here's the surprising psychology behind imposter syndrome—and how to finally believe in your own competence.",
  "date": "2026-03-12",
  "url": "https://boldlybalance.life/posts/confidence-paradox-imposter-syndrome.html",
  "generatedAt": "2026-03-20T10:26:31.474Z"
}